{
  "value": {
    "cachedAt": "2026-06-25T16:58:32.840Z",
    "profile": {
      "login": "karma4O4",
      "id": 185616599,
      "node_id": "U_kgDOCxBI1w",
      "avatar_url": "https://avatars.githubusercontent.com/u/185616599?v=4",
      "gravatar_id": "",
      "url": "https://api.github.com/users/karma4O4",
      "html_url": "https://github.com/karma4O4",
      "followers_url": "https://api.github.com/users/karma4O4/followers",
      "following_url": "https://api.github.com/users/karma4O4/following{/other_user}",
      "gists_url": "https://api.github.com/users/karma4O4/gists{/gist_id}",
      "starred_url": "https://api.github.com/users/karma4O4/starred{/owner}{/repo}",
      "subscriptions_url": "https://api.github.com/users/karma4O4/subscriptions",
      "organizations_url": "https://api.github.com/users/karma4O4/orgs",
      "repos_url": "https://api.github.com/users/karma4O4/repos",
      "events_url": "https://api.github.com/users/karma4O4/events{/privacy}",
      "received_events_url": "https://api.github.com/users/karma4O4/received_events",
      "type": "User",
      "user_view_type": "public",
      "site_admin": false,
      "name": "HArsil",
      "company": null,
      "blog": "",
      "location": null,
      "email": null,
      "hireable": null,
      "bio": null,
      "twitter_username": null,
      "public_repos": 21,
      "public_gists": 0,
      "followers": 0,
      "following": 0,
      "created_at": "2024-10-19T14:28:01Z",
      "updated_at": "2026-02-23T16:27:41Z"
    },
    "prs": [
      {
        "url": "https://api.github.com/repos/JACOBIAN01/github-actions-starter/issues/1",
        "repository_url": "https://api.github.com/repos/JACOBIAN01/github-actions-starter",
        "labels_url": "https://api.github.com/repos/JACOBIAN01/github-actions-starter/issues/1/labels{/name}",
        "comments_url": "https://api.github.com/repos/JACOBIAN01/github-actions-starter/issues/1/comments",
        "events_url": "https://api.github.com/repos/JACOBIAN01/github-actions-starter/issues/1/events",
        "html_url": "https://github.com/JACOBIAN01/github-actions-starter/pull/1",
        "id": 4308431533,
        "node_id": "PR_kwDOSJaPh87Ul3jV",
        "number": 1,
        "title": "Create BACKEND-TESTING.YML",
        "user": {
          "login": "karma4O4",
          "id": 185616599,
          "node_id": "U_kgDOCxBI1w",
          "avatar_url": "https://avatars.githubusercontent.com/u/185616599?v=4",
          "gravatar_id": "",
          "url": "https://api.github.com/users/karma4O4",
          "html_url": "https://github.com/karma4O4",
          "followers_url": "https://api.github.com/users/karma4O4/followers",
          "following_url": "https://api.github.com/users/karma4O4/following{/other_user}",
          "gists_url": "https://api.github.com/users/karma4O4/gists{/gist_id}",
          "starred_url": "https://api.github.com/users/karma4O4/starred{/owner}{/repo}",
          "subscriptions_url": "https://api.github.com/users/karma4O4/subscriptions",
          "organizations_url": "https://api.github.com/users/karma4O4/orgs",
          "repos_url": "https://api.github.com/users/karma4O4/repos",
          "events_url": "https://api.github.com/users/karma4O4/events{/privacy}",
          "received_events_url": "https://api.github.com/users/karma4O4/received_events",
          "type": "User",
          "user_view_type": "public",
          "site_admin": false
        },
        "labels": [],
        "state": "open",
        "locked": false,
        "assignees": [],
        "milestone": null,
        "comments": 1,
        "created_at": "2026-04-22T10:47:17Z",
        "updated_at": "2026-04-22T10:47:35Z",
        "closed_at": null,
        "assignee": null,
        "author_association": "NONE",
        "active_lock_reason": null,
        "draft": false,
        "pull_request": {
          "url": "https://api.github.com/repos/JACOBIAN01/github-actions-starter/pulls/1",
          "html_url": "https://github.com/JACOBIAN01/github-actions-starter/pull/1",
          "diff_url": "https://github.com/JACOBIAN01/github-actions-starter/pull/1.diff",
          "patch_url": "https://github.com/JACOBIAN01/github-actions-starter/pull/1.patch",
          "merged_at": null
        },
        "body": null,
        "reactions": {
          "url": "https://api.github.com/repos/JACOBIAN01/github-actions-starter/issues/1/reactions",
          "total_count": 0,
          "+1": 0,
          "-1": 0,
          "laugh": 0,
          "hooray": 0,
          "confused": 0,
          "heart": 0,
          "rocket": 0,
          "eyes": 0
        },
        "timeline_url": "https://api.github.com/repos/JACOBIAN01/github-actions-starter/issues/1/timeline",
        "performed_via_github_app": null,
        "state_reason": null,
        "score": 1
      },
      {
        "url": "https://api.github.com/repos/drawdb-io/drawdb/issues/803",
        "repository_url": "https://api.github.com/repos/drawdb-io/drawdb",
        "labels_url": "https://api.github.com/repos/drawdb-io/drawdb/issues/803/labels{/name}",
        "comments_url": "https://api.github.com/repos/drawdb-io/drawdb/issues/803/comments",
        "events_url": "https://api.github.com/repos/drawdb-io/drawdb/issues/803/events",
        "html_url": "https://github.com/drawdb-io/drawdb/pull/803",
        "id": 3693078490,
        "node_id": "PR_kwDOJ8NLw862-9zq",
        "number": 803,
        "title": "fixed-794",
        "user": {
          "login": "karma4O4",
          "id": 185616599,
          "node_id": "U_kgDOCxBI1w",
          "avatar_url": "https://avatars.githubusercontent.com/u/185616599?v=4",
          "gravatar_id": "",
          "url": "https://api.github.com/users/karma4O4",
          "html_url": "https://github.com/karma4O4",
          "followers_url": "https://api.github.com/users/karma4O4/followers",
          "following_url": "https://api.github.com/users/karma4O4/following{/other_user}",
          "gists_url": "https://api.github.com/users/karma4O4/gists{/gist_id}",
          "starred_url": "https://api.github.com/users/karma4O4/starred{/owner}{/repo}",
          "subscriptions_url": "https://api.github.com/users/karma4O4/subscriptions",
          "organizations_url": "https://api.github.com/users/karma4O4/orgs",
          "repos_url": "https://api.github.com/users/karma4O4/repos",
          "events_url": "https://api.github.com/users/karma4O4/events{/privacy}",
          "received_events_url": "https://api.github.com/users/karma4O4/received_events",
          "type": "User",
          "user_view_type": "public",
          "site_admin": false
        },
        "labels": [],
        "state": "closed",
        "locked": false,
        "assignees": [],
        "milestone": null,
        "comments": 1,
        "created_at": "2025-12-04T06:08:09Z",
        "updated_at": "2025-12-04T06:56:43Z",
        "closed_at": "2025-12-04T06:56:43Z",
        "assignee": null,
        "author_association": "NONE",
        "issue_field_values": [],
        "type": null,
        "active_lock_reason": null,
        "draft": false,
        "pull_request": {
          "url": "https://api.github.com/repos/drawdb-io/drawdb/pulls/803",
          "html_url": "https://github.com/drawdb-io/drawdb/pull/803",
          "diff_url": "https://github.com/drawdb-io/drawdb/pull/803.diff",
          "patch_url": "https://github.com/drawdb-io/drawdb/pull/803.patch",
          "merged_at": null
        },
        "body": "This PR adds the feature requested in Issue #794: natural-language database schema generation.\r\n\r\n✔ What’s Included\r\n\r\nNew AIGenerationModal for user prompts\r\n\r\naiUtils.js for calling the AI model and parsing results\r\n\r\nIntegration into ControlPanel with an “AI Schema Generator” button\r\n\r\nAutomatic creation of tables and relationships from generated JSON\r\n\r\n✔ Result\r\n\r\nUsers can now describe their database in plain English, and DrawDB will generate the full schema automatically.",
        "reactions": {
          "url": "https://api.github.com/repos/drawdb-io/drawdb/issues/803/reactions",
          "total_count": 0,
          "+1": 0,
          "-1": 0,
          "laugh": 0,
          "hooray": 0,
          "confused": 0,
          "heart": 0,
          "rocket": 0,
          "eyes": 0
        },
        "timeline_url": "https://api.github.com/repos/drawdb-io/drawdb/issues/803/timeline",
        "performed_via_github_app": null,
        "state_reason": null,
        "score": 1
      },
      {
        "url": "https://api.github.com/repos/libuv/libuv/issues/4958",
        "repository_url": "https://api.github.com/repos/libuv/libuv",
        "labels_url": "https://api.github.com/repos/libuv/libuv/issues/4958/labels{/name}",
        "comments_url": "https://api.github.com/repos/libuv/libuv/issues/4958/comments",
        "events_url": "https://api.github.com/repos/libuv/libuv/issues/4958/events",
        "html_url": "https://github.com/libuv/libuv/pull/4958",
        "id": 3690827184,
        "node_id": "PR_kwDOAOIGQ8623WsL",
        "number": 4958,
        "title": "docs: add copybutton sphinx extension",
        "user": {
          "login": "karma4O4",
          "id": 185616599,
          "node_id": "U_kgDOCxBI1w",
          "avatar_url": "https://avatars.githubusercontent.com/u/185616599?v=4",
          "gravatar_id": "",
          "url": "https://api.github.com/users/karma4O4",
          "html_url": "https://github.com/karma4O4",
          "followers_url": "https://api.github.com/users/karma4O4/followers",
          "following_url": "https://api.github.com/users/karma4O4/following{/other_user}",
          "gists_url": "https://api.github.com/users/karma4O4/gists{/gist_id}",
          "starred_url": "https://api.github.com/users/karma4O4/starred{/owner}{/repo}",
          "subscriptions_url": "https://api.github.com/users/karma4O4/subscriptions",
          "organizations_url": "https://api.github.com/users/karma4O4/orgs",
          "repos_url": "https://api.github.com/users/karma4O4/repos",
          "events_url": "https://api.github.com/users/karma4O4/events{/privacy}",
          "received_events_url": "https://api.github.com/users/karma4O4/received_events",
          "type": "User",
          "user_view_type": "public",
          "site_admin": false
        },
        "labels": [],
        "state": "closed",
        "locked": false,
        "assignees": [],
        "milestone": null,
        "comments": 2,
        "created_at": "2025-12-03T15:57:02Z",
        "updated_at": "2026-03-17T02:35:00Z",
        "closed_at": "2026-03-17T02:34:59Z",
        "assignee": null,
        "author_association": "CONTRIBUTOR",
        "issue_field_values": [],
        "type": null,
        "active_lock_reason": null,
        "draft": false,
        "pull_request": {
          "url": "https://api.github.com/repos/libuv/libuv/pulls/4958",
          "html_url": "https://github.com/libuv/libuv/pull/4958",
          "diff_url": "https://github.com/libuv/libuv/pull/4958.diff",
          "patch_url": "https://github.com/libuv/libuv/pull/4958.patch",
          "merged_at": "2026-03-17T02:34:59Z"
        },
        "body": "Adds a Copy button to all code blocks in the libuv documentation. This improves usability by allowing users to copy code examples with a single click instead of manually selecting text.\r\n\r\nThe change includes:\r\nA small JavaScript file that injects a “Copy” button into each code block and copies its content using navigator.clipboard.writeText().\r\nMinimal CSS to position and style the button.\r\nUpdates to docs/conf.py to load the new JS and CSS assets.\r\n\r\nThis affects only the documentation website and does not modify any core libuv code.",
        "reactions": {
          "url": "https://api.github.com/repos/libuv/libuv/issues/4958/reactions",
          "total_count": 0,
          "+1": 0,
          "-1": 0,
          "laugh": 0,
          "hooray": 0,
          "confused": 0,
          "heart": 0,
          "rocket": 0,
          "eyes": 0
        },
        "timeline_url": "https://api.github.com/repos/libuv/libuv/issues/4958/timeline",
        "performed_via_github_app": null,
        "state_reason": null,
        "score": 1
      },
      {
        "url": "https://api.github.com/repos/shikijs/shiki/issues/1192",
        "repository_url": "https://api.github.com/repos/shikijs/shiki",
        "labels_url": "https://api.github.com/repos/shikijs/shiki/issues/1192/labels{/name}",
        "comments_url": "https://api.github.com/repos/shikijs/shiki/issues/1192/comments",
        "events_url": "https://api.github.com/repos/shikijs/shiki/issues/1192/events",
        "html_url": "https://github.com/shikijs/shiki/pull/1192",
        "id": 3689007457,
        "node_id": "PR_kwDOCUGEHM62xKJX",
        "number": 1192,
        "title": "Fixed #619",
        "user": {
          "login": "karma4O4",
          "id": 185616599,
          "node_id": "U_kgDOCxBI1w",
          "avatar_url": "https://avatars.githubusercontent.com/u/185616599?v=4",
          "gravatar_id": "",
          "url": "https://api.github.com/users/karma4O4",
          "html_url": "https://github.com/karma4O4",
          "followers_url": "https://api.github.com/users/karma4O4/followers",
          "following_url": "https://api.github.com/users/karma4O4/following{/other_user}",
          "gists_url": "https://api.github.com/users/karma4O4/gists{/gist_id}",
          "starred_url": "https://api.github.com/users/karma4O4/starred{/owner}{/repo}",
          "subscriptions_url": "https://api.github.com/users/karma4O4/subscriptions",
          "organizations_url": "https://api.github.com/users/karma4O4/orgs",
          "repos_url": "https://api.github.com/users/karma4O4/repos",
          "events_url": "https://api.github.com/users/karma4O4/events{/privacy}",
          "received_events_url": "https://api.github.com/users/karma4O4/received_events",
          "type": "User",
          "user_view_type": "public",
          "site_admin": false
        },
        "labels": [
          {
            "id": 9761935103,
            "node_id": "LA_kwDOCUGEHM8AAAACRdtO_w",
            "url": "https://api.github.com/repos/shikijs/shiki/labels/seems-ai-generated",
            "name": "seems-ai-generated",
            "color": "B60205",
            "default": false,
            "description": "We label this as a rejection to PR that seems to be AI generated. Please do not do that."
          }
        ],
        "state": "closed",
        "locked": false,
        "assignees": [],
        "milestone": null,
        "comments": 2,
        "created_at": "2025-12-03T08:12:54Z",
        "updated_at": "2025-12-05T05:16:48Z",
        "closed_at": "2025-12-03T10:17:57Z",
        "assignee": null,
        "author_association": "NONE",
        "issue_field_values": [],
        "type": null,
        "active_lock_reason": null,
        "draft": false,
        "pull_request": {
          "url": "https://api.github.com/repos/shikijs/shiki/pulls/1192",
          "html_url": "https://github.com/shikijs/shiki/pull/1192",
          "diff_url": "https://github.com/shikijs/shiki/pull/1192.diff",
          "patch_url": "https://github.com/shikijs/shiki/pull/1192.patch",
          "merged_at": null
        },
        "body": "### Description\r\n\r\nFixes #619.\r\n\r\nThis PR corrects an off-by-one behavior in the notation-highlighter transformer\r\n(`@shikijs/transformers`) where `// [!code highlight:N]` unintentionally\r\nincluded the comment's own line in the computed highlight range.\r\n\r\n**Change made**\r\n- Shift the computed range so that highlighting begins on the line *after*\r\n  the notation comment:\r\n  ```ts\r\n  // before\r\n  start = lineNumber\r\n  end   = lineNumber + count\r\n\r\n  // after\r\n  start = lineNumber + 1\r\n  end   = lineNumber + 1 + count\r\n",
        "reactions": {
          "url": "https://api.github.com/repos/shikijs/shiki/issues/1192/reactions",
          "total_count": 0,
          "+1": 0,
          "-1": 0,
          "laugh": 0,
          "hooray": 0,
          "confused": 0,
          "heart": 0,
          "rocket": 0,
          "eyes": 0
        },
        "timeline_url": "https://api.github.com/repos/shikijs/shiki/issues/1192/timeline",
        "performed_via_github_app": null,
        "state_reason": null,
        "score": 1
      },
      {
        "url": "https://api.github.com/repos/shikijs/shiki/issues/1183",
        "repository_url": "https://api.github.com/repos/shikijs/shiki",
        "labels_url": "https://api.github.com/repos/shikijs/shiki/issues/1183/labels{/name}",
        "comments_url": "https://api.github.com/repos/shikijs/shiki/issues/1183/comments",
        "events_url": "https://api.github.com/repos/shikijs/shiki/issues/1183/events",
        "html_url": "https://github.com/shikijs/shiki/pull/1183",
        "id": 3687386965,
        "node_id": "PR_kwDOCUGEHM62r0IU",
        "number": 1183,
        "title": "Issue 853 fix bug",
        "user": {
          "login": "karma4O4",
          "id": 185616599,
          "node_id": "U_kgDOCxBI1w",
          "avatar_url": "https://avatars.githubusercontent.com/u/185616599?v=4",
          "gravatar_id": "",
          "url": "https://api.github.com/users/karma4O4",
          "html_url": "https://github.com/karma4O4",
          "followers_url": "https://api.github.com/users/karma4O4/followers",
          "following_url": "https://api.github.com/users/karma4O4/following{/other_user}",
          "gists_url": "https://api.github.com/users/karma4O4/gists{/gist_id}",
          "starred_url": "https://api.github.com/users/karma4O4/starred{/owner}{/repo}",
          "subscriptions_url": "https://api.github.com/users/karma4O4/subscriptions",
          "organizations_url": "https://api.github.com/users/karma4O4/orgs",
          "repos_url": "https://api.github.com/users/karma4O4/repos",
          "events_url": "https://api.github.com/users/karma4O4/events{/privacy}",
          "received_events_url": "https://api.github.com/users/karma4O4/received_events",
          "type": "User",
          "user_view_type": "public",
          "site_admin": false
        },
        "labels": [
          {
            "id": 9761935103,
            "node_id": "LA_kwDOCUGEHM8AAAACRdtO_w",
            "url": "https://api.github.com/repos/shikijs/shiki/labels/seems-ai-generated",
            "name": "seems-ai-generated",
            "color": "B60205",
            "default": false,
            "description": "We label this as a rejection to PR that seems to be AI generated. Please do not do that."
          }
        ],
        "state": "closed",
        "locked": false,
        "assignees": [],
        "milestone": null,
        "comments": 3,
        "created_at": "2025-12-02T20:12:12Z",
        "updated_at": "2025-12-08T13:35:10Z",
        "closed_at": "2025-12-03T05:11:00Z",
        "assignee": null,
        "author_association": "NONE",
        "issue_field_values": [],
        "type": null,
        "active_lock_reason": null,
        "draft": false,
        "pull_request": {
          "url": "https://api.github.com/repos/shikijs/shiki/pulls/1183",
          "html_url": "https://github.com/shikijs/shiki/pull/1183",
          "diff_url": "https://github.com/shikijs/shiki/pull/1183.diff",
          "patch_url": "https://github.com/shikijs/shiki/pull/1183.patch",
          "merged_at": null
        },
        "body": "### Description\r\n\r\nThis PR improves performance and clarity in the Markdown-It integration by preventing all languages from being loaded by default.\r\n\r\nPreviously, the “Getting Started” example automatically loaded **every available language**, which caused slow startup times and poor performance.\r\n\r\nThis PR introduces the following changes:\r\n\r\n- The example now loads **only necessary languages** explicitly.\r\n- A **warning message** is displayed when all languages are being loaded, informing users of:\r\n  - The **number of languages** being loaded,\r\n  - A recommendation to load only required languages,\r\n  - An example showing how to configure language loading properly.\r\n- Users can disable warnings using `warnings: false` in the options.\r\n\r\nThese updates help users avoid performance issues and understand how to load languages efficiently.\r\n\r\n### Linked Issues\r\n\r\nfixes #853\r\n\r\n",
        "reactions": {
          "url": "https://api.github.com/repos/shikijs/shiki/issues/1183/reactions",
          "total_count": 0,
          "+1": 0,
          "-1": 0,
          "laugh": 0,
          "hooray": 0,
          "confused": 0,
          "heart": 0,
          "rocket": 0,
          "eyes": 0
        },
        "timeline_url": "https://api.github.com/repos/shikijs/shiki/issues/1183/timeline",
        "performed_via_github_app": null,
        "state_reason": null,
        "score": 1
      },
      {
        "url": "https://api.github.com/repos/processing/p5.js/issues/8313",
        "repository_url": "https://api.github.com/repos/processing/p5.js",
        "labels_url": "https://api.github.com/repos/processing/p5.js/issues/8313/labels{/name}",
        "comments_url": "https://api.github.com/repos/processing/p5.js/issues/8313/comments",
        "events_url": "https://api.github.com/repos/processing/p5.js/issues/8313/events",
        "html_url": "https://github.com/processing/p5.js/pull/8313",
        "id": 3686693272,
        "node_id": "PR_kwDOAICKaM62pdD6",
        "number": 8313,
        "title": "docs(es): sync Spanish “Steward Guidelines” page with latest English version (remove outdated Grunt references)",
        "user": {
          "login": "karma4O4",
          "id": 185616599,
          "node_id": "U_kgDOCxBI1w",
          "avatar_url": "https://avatars.githubusercontent.com/u/185616599?v=4",
          "gravatar_id": "",
          "url": "https://api.github.com/users/karma4O4",
          "html_url": "https://github.com/karma4O4",
          "followers_url": "https://api.github.com/users/karma4O4/followers",
          "following_url": "https://api.github.com/users/karma4O4/following{/other_user}",
          "gists_url": "https://api.github.com/users/karma4O4/gists{/gist_id}",
          "starred_url": "https://api.github.com/users/karma4O4/starred{/owner}{/repo}",
          "subscriptions_url": "https://api.github.com/users/karma4O4/subscriptions",
          "organizations_url": "https://api.github.com/users/karma4O4/orgs",
          "repos_url": "https://api.github.com/users/karma4O4/repos",
          "events_url": "https://api.github.com/users/karma4O4/events{/privacy}",
          "received_events_url": "https://api.github.com/users/karma4O4/received_events",
          "type": "User",
          "user_view_type": "public",
          "site_admin": false
        },
        "labels": [],
        "state": "closed",
        "locked": false,
        "assignees": [],
        "milestone": null,
        "comments": 1,
        "created_at": "2025-12-02T16:46:46Z",
        "updated_at": "2025-12-05T16:00:13Z",
        "closed_at": "2025-12-05T16:00:13Z",
        "assignee": null,
        "author_association": "NONE",
        "issue_field_values": [],
        "type": null,
        "active_lock_reason": null,
        "draft": false,
        "pull_request": {
          "url": "https://api.github.com/repos/processing/p5.js/pulls/8313",
          "html_url": "https://github.com/processing/p5.js/pull/8313",
          "diff_url": "https://github.com/processing/p5.js/pull/8313.diff",
          "patch_url": "https://github.com/processing/p5.js/pull/8313.patch",
          "merged_at": null
        },
        "body": "This PR updates the Spanish version of the Steward Guidelines to match the latest English version for p5.js 2.x.",
        "reactions": {
          "url": "https://api.github.com/repos/processing/p5.js/issues/8313/reactions",
          "total_count": 0,
          "+1": 0,
          "-1": 0,
          "laugh": 0,
          "hooray": 0,
          "confused": 0,
          "heart": 0,
          "rocket": 0,
          "eyes": 0
        },
        "timeline_url": "https://api.github.com/repos/processing/p5.js/issues/8313/timeline",
        "performed_via_github_app": null,
        "state_reason": null,
        "score": 1
      },
      {
        "url": "https://api.github.com/repos/shikijs/shiki/issues/1177",
        "repository_url": "https://api.github.com/repos/shikijs/shiki",
        "labels_url": "https://api.github.com/repos/shikijs/shiki/issues/1177/labels{/name}",
        "comments_url": "https://api.github.com/repos/shikijs/shiki/issues/1177/comments",
        "events_url": "https://api.github.com/repos/shikijs/shiki/issues/1177/events",
        "html_url": "https://github.com/shikijs/shiki/pull/1177",
        "id": 3685199108,
        "node_id": "PR_kwDOCUGEHM62kXYU",
        "number": 1177,
        "title": "Add example showing how to get all tokens for a filetype (#965)",
        "user": {
          "login": "karma4O4",
          "id": 185616599,
          "node_id": "U_kgDOCxBI1w",
          "avatar_url": "https://avatars.githubusercontent.com/u/185616599?v=4",
          "gravatar_id": "",
          "url": "https://api.github.com/users/karma4O4",
          "html_url": "https://github.com/karma4O4",
          "followers_url": "https://api.github.com/users/karma4O4/followers",
          "following_url": "https://api.github.com/users/karma4O4/following{/other_user}",
          "gists_url": "https://api.github.com/users/karma4O4/gists{/gist_id}",
          "starred_url": "https://api.github.com/users/karma4O4/starred{/owner}{/repo}",
          "subscriptions_url": "https://api.github.com/users/karma4O4/subscriptions",
          "organizations_url": "https://api.github.com/users/karma4O4/orgs",
          "repos_url": "https://api.github.com/users/karma4O4/repos",
          "events_url": "https://api.github.com/users/karma4O4/events{/privacy}",
          "received_events_url": "https://api.github.com/users/karma4O4/received_events",
          "type": "User",
          "user_view_type": "public",
          "site_admin": false
        },
        "labels": [
          {
            "id": 9761935103,
            "node_id": "LA_kwDOCUGEHM8AAAACRdtO_w",
            "url": "https://api.github.com/repos/shikijs/shiki/labels/seems-ai-generated",
            "name": "seems-ai-generated",
            "color": "B60205",
            "default": false,
            "description": "We label this as a rejection to PR that seems to be AI generated. Please do not do that."
          }
        ],
        "state": "closed",
        "locked": false,
        "assignees": [],
        "milestone": null,
        "comments": 3,
        "created_at": "2025-12-02T10:34:20Z",
        "updated_at": "2025-12-08T13:35:17Z",
        "closed_at": "2025-12-03T05:07:47Z",
        "assignee": null,
        "author_association": "NONE",
        "issue_field_values": [],
        "type": null,
        "active_lock_reason": null,
        "draft": false,
        "pull_request": {
          "url": "https://api.github.com/repos/shikijs/shiki/pulls/1177",
          "html_url": "https://github.com/shikijs/shiki/pull/1177",
          "diff_url": "https://github.com/shikijs/shiki/pull/1177.diff",
          "patch_url": "https://github.com/shikijs/shiki/pull/1177.patch",
          "merged_at": null
        },
        "body": "This PR adds an example to README.md demonstrating how to use Shiki's `codeToTokens()` API to get all tokens for a given filetype.\r\n\r\n- Shows a small JavaScript snippet using `getHighlighter` and `codeToTokens`.\r\n- Provides explanation of the output tokens (`content` and `color`).\r\n- Adds a tip about where to find all possible token types in Shiki's TextMate grammar files.\r\n\r\nThis resolves issue #965.\r\n",
        "reactions": {
          "url": "https://api.github.com/repos/shikijs/shiki/issues/1177/reactions",
          "total_count": 0,
          "+1": 0,
          "-1": 0,
          "laugh": 0,
          "hooray": 0,
          "confused": 0,
          "heart": 0,
          "rocket": 0,
          "eyes": 0
        },
        "timeline_url": "https://api.github.com/repos/shikijs/shiki/issues/1177/timeline",
        "performed_via_github_app": null,
        "state_reason": null,
        "score": 1
      }
    ],
    "issues": []
  },
  "expiresAt": 1784998712845
}